{"chunk_definitions":[{"row":65,"row_count":1,"visible":true,"expansion_state":0,"options":{"engine":"r","echo":false,"message":false,"warning":false,"fig.cap":"Oversikt regler kontrolldiagram","label":"unnamed-chunk-38"},"document_id":"2A9A594D","chunk_id":"cp5o825t6wo9x","chunk_label":"unnamed-chunk-3"},{"row":125,"row_count":1,"visible":true,"expansion_state":0,"options":{"engine":"r","echo":false,"message":false,"warning":false,"fig.cap":"p-diagram data","label":"unnamed-chunk-1"},"document_id":"2A9A594D","chunk_id":"cxiofrokc7l02","chunk_label":"unnamed-chunk-5"},{"row":132,"row_count":1,"visible":true,"expansion_state":0,"options":{"engine":"r","echo":false,"eval":true,"label":"unnamed-chunk-2"},"document_id":"2A9A594D","chunk_id":"c7jxra36pupa8","chunk_label":"unnamed-chunk-6"},{"row":175,"row_count":1,"visible":true,"expansion_state":0,"options":{"engine":"r","echo":false,"message":false,"warning":false,"fig.cap":"p'-diagram data","label":"unnamed-chunk-36"},"document_id":"2A9A594D","chunk_id":"c4q03j1gavmo9","chunk_label":"unnamed-chunk-8"},{"row":181,"row_count":1,"visible":true,"expansion_state":0,"options":{"engine":"r","echo":false,"eval":true,"label":"unnamed-chunk-40"},"document_id":"2A9A594D","chunk_id":"cc15dbecw0dz7","chunk_label":"unnamed-chunk-9"},{"row":228,"row_count":1,"visible":true,"expansion_state":0,"options":{"engine":"r","echo":false,"message":false,"warning":false,"fig.cap":"p'-diagram data","label":"unnamed-chunk-1"},"document_id":"2A9A594D","chunk_id":"c6hcwr25ru04s","chunk_label":"unnamed-chunk-11"},{"row":234,"row_count":1,"visible":true,"expansion_state":0,"options":{"engine":"r","echo":false,"eval":true,"label":"unnamed-chunk-2"},"document_id":"2A9A594D","chunk_id":"c3zxml0rcbwv8","chunk_label":"unnamed-chunk-12"},{"row":276,"row_count":1,"visible":true,"expansion_state":0,"options":{"engine":"r","echo":false,"message":false,"warning":false,"fig.cap":"p'-diagram data","label":"unnamed-chunk-9"},"document_id":"2A9A594D","chunk_id":"csgscfhtkijsq","chunk_label":"unnamed-chunk-14"},{"row":305,"row_count":1,"visible":true,"expansion_state":0,"options":{"engine":"r","echo":false,"eval":true,"label":"unnamed-chunk-12"},"document_id":"2A9A594D","chunk_id":"c5e7elag822fp","chunk_label":"unnamed-chunk-17"},{"row":327,"row_count":1,"visible":true,"expansion_state":0,"options":{"engine":"r","echo":false,"message":false,"warning":false,"fig.cap":"u-diagram data","label":"unnamed-chunk-11"},"document_id":"2A9A594D","chunk_id":"ccwwsu1k0gzvp","chunk_label":"unnamed-chunk-18"},{"row":456,"row_count":1,"visible":true,"expansion_state":0,"options":{"engine":"r","echo":false,"message":false,"warning":false,"fig.cap":"IMR-diagram data","label":"unnamed-chunk-1"},"document_id":"2A9A594D","chunk_id":"cmhjt1qtiud9w","chunk_label":"unnamed-chunk-24"},{"row":505,"row_count":1,"visible":true,"expansion_state":0,"options":{"engine":"r","echo":false,"message":false,"warning":false,"fig.cap":"XbarR-diagram data","label":"unnamed-chunk-19"},"document_id":"2A9A594D","chunk_id":"c9klhhlwt1gg8","chunk_label":"unnamed-chunk-27"}],"doc_write_time":1634839728}